alembic_offline/__init__.py
alembic_offline/api.py
alembic_offline/decorators.py
alembic_offline/operations.py
alembic_offline-2.0.0.dist-info/METADATA
alembic_offline-2.0.0.dist-info/WHEEL
alembic_offline-2.0.0.dist-info/RECORD
