Metadata-Version: 2.3
Name: alembic-offline
Version: 2.0.0
Summary: Offline extensions for Alembic database migration framework for SQLAlchemy
Project-URL: Homepage, https://github.com/paylogic/alembic-offline
Project-URL: Issues, https://github.com/paylogic/alembic-offline/issues
Author: Anatoly Bubenkov
Author-email: Paylogic International <developers@paylogic.com>
Classifier: Development Status :: 4 - Beta
Classifier: Environment :: Other Environment
Classifier: Intended Audience :: Developers
Classifier: Intended Audience :: System Administrators
Classifier: License :: OSI Approved :: MIT License
Classifier: Operating System :: POSIX :: Linux
Classifier: Operating System :: Unix
Classifier: Programming Language :: Python
Classifier: Programming Language :: Python :: 3
Classifier: Programming Language :: Python :: 3.9
Classifier: Programming Language :: Python :: 3.10
Classifier: Programming Language :: Python :: 3.11
Classifier: Programming Language :: Python :: 3.12
Requires-Python: >=3.8
Requires-Dist: alembic>=1.13.1
